cv_gg/__init__.py
cv_gg/core.py
cv_gg/data/__init__.py
cv_gg/data/all_CV.txt
cv_gg-0.1.0.dist-info/METADATA
cv_gg-0.1.0.dist-info/WHEEL
cv_gg-0.1.0.dist-info/top_level.txt
cv_gg-0.1.0.dist-info/RECORD
