Metadata-Version: 2.2
Name: cv_gg
Version: 0.1.0
Summary: ACV - скат по задачам
Classifier: Programming Language :: Python :: 3
Classifier: License :: OSI Approved :: MIT License
Classifier: Operating System :: OS Independent
Requires-Python: >=3.6
Dynamic: classifier
Dynamic: description-content-type
Dynamic: requires-python
Dynamic: summary
